AUTHORS.md
CHANGELOG.md
LICENSE
MANIFEST.in
README.md
requirements.txt
setup.py
utils_py/Point.py
utils_py/Polygon.py
utils_py/TimeRange.py
utils_py/__init__.py
utils_py/const.py
utils_py/decorator.py
utils_py/geo_util.py
utils_py/math_util.py
utils_py/time_seg_util.py
utils_py/time_util.py
utils_py.egg-info/PKG-INFO
utils_py.egg-info/SOURCES.txt
utils_py.egg-info/dependency_links.txt
utils_py.egg-info/not-zip-safe
utils_py.egg-info/requires.txt
utils_py.egg-info/top_level.txt