Metadata-Version: 1.1
Name: utils-py
Version: 0.3.0
Summary: Utility package for python
Home-page: https://github.com/ytjia/utils-py
Author: Y. Jia
Author-email: ytjia.zju@gmail.com
License: Apache 2.0
Keywords: python utility
Platform: UNKNOWN
Classifier: Intended Audience :: Developers
Classifier: License :: OSI Approved :: Apache Software License
Classifier: Programming Language :: Python :: 2.7
Classifier: Programming Language :: Python :: 3.6
Classifier: Topic :: Utilities
